flexcv/__init__.py
flexcv/_data.py
flexcv/core.py
flexcv/fold_logging.py
flexcv/fold_results_handling.py
flexcv/interface.py
flexcv/merf.py
flexcv/metrics.py
flexcv/model_mapping.py
flexcv/model_mapping.yaml
flexcv/model_postprocessing.py
flexcv/model_selection.py
flexcv/models.py
flexcv/plot.py
flexcv/repeated.py
flexcv/results_handling.py
flexcv/run.py
flexcv/split.py
flexcv/stratification.py
flexcv/synthesizer.py
flexcv/utilities.py
flexcv/yaml_parser.py
flexcv-24.0b0.dist-info/LICENSE
flexcv-24.0b0.dist-info/METADATA
flexcv-24.0b0.dist-info/WHEEL
flexcv-24.0b0.dist-info/top_level.txt
flexcv-24.0b0.dist-info/RECORD
