Metadata-Version: 2.1
Name: flexcv
Version: 24.0b0
Summary: Easy and flexible nested cross validation for tabular data in python.
Author: Patrick Blättermann, Siegbert Versümer
Author-email: Fabian Rosenthal <rosenthal.fabian@gmail.com>
License: MIT License
Project-URL: Homepage, https://github.com/radlfabs/flexcv
Project-URL: Bug Tracker, https://github.com/radlfabs/flexcv/issues
Project-URL: Docs, https://radlfabs.github.io/flexcv
Keywords: machine learning,cross validation
Classifier: License :: OSI Approved :: MIT License
Classifier: Programming Language :: Python
Classifier: Programming Language :: Python :: 3
Requires-Python: <3.12,>=3.10
License-File: LICENSE
Requires-Dist: matplotlib >=3.5.0
Requires-Dist: numpy >=1.23.4
Requires-Dist: openpyxl >=3.1.2
Requires-Dist: optuna >=3.4.0
Requires-Dist: pandas >=1.5.1
Requires-Dist: scikit-learn >=1.3.2
Requires-Dist: seaborn >=0.13.0
Requires-Dist: shap >=0.43.0
Requires-Dist: statsmodels >=0.14.0
Requires-Dist: tqdm >=4.66.1
Requires-Dist: xgboost >=2.0.1
Requires-Dist: neptune >=1.8.2
Requires-Dist: neptune-optuna >=1.1.0
Requires-Dist: neptune-xgboost >=1.1.1
Requires-Dist: neptune-sklearn >=2.1.0
Requires-Dist: pyyaml
Requires-Dist: scipy <1.12
Provides-Extra: dev
Requires-Dist: bumpver ; extra == 'dev'
Requires-Dist: pytest ; extra == 'dev'
Requires-Dist: pytest-cov ; extra == 'dev'
Requires-Dist: mkdocs ; extra == 'dev'
Requires-Dist: mkdocstrings ; extra == 'dev'
Requires-Dist: mktestdocs ; extra == 'dev'
Requires-Dist: mkdocs-material ; extra == 'dev'
Requires-Dist: mkdocstrings-python ; extra == 'dev'
Requires-Dist: check-manifest ; extra == 'dev'
Requires-Dist: pip-tools ; extra == 'dev'
Requires-Dist: twine ; extra == 'dev'
Requires-Dist: black ; extra == 'dev'
Requires-Dist: isort ; extra == 'dev'
Provides-Extra: docs
Requires-Dist: mkdocs ; extra == 'docs'
Requires-Dist: mkdocstrings ; extra == 'docs'
Requires-Dist: mkdocs-material ; extra == 'docs'
